py_rust_stemmers-0.1.5.dist-info/METADATA
py_rust_stemmers-0.1.5.dist-info/WHEEL
py_rust_stemmers-0.1.5.dist-info/licenses/LICENSE
py_rust_stemmers/__init__.py
py_rust_stemmers/py_rust_stemmers.cpython-311-arm-linux-gnueabihf.so
py_rust_stemmers-0.1.5.dist-info/RECORD
