Metadata-Version: 2.3
Name: py_rust_stemmers
Version: 0.1.5
License-File: LICENSE
Summary: Fast and parallel snowball stemmer
